[
  {
    "id": "B002G392ZI",
    "title": "ARCTIC Freezer 7 Pro - Compact Multi-Compatible Tower CPU Cooler | 92 Mm PWM Fan | For AMD AM4 And Intel 115x CPU | Recommended Up To 115 W TDP",
    "link": "https://amazon.com/dp/B002G392ZI?tag=pcbuildcompat-20",
    "img": "https://images-na.ssl-images-amazon.com/images/I/51xBPLiRpkL._SL75_.jpg",
    "price": 0,
    "brand": "ARCTIC",
    "model": "DCACO-FP701-CSA01",
    "rpm": "900 - 2500 RPM",
    "color": "N/A",
    "noiseLevel": "N/A"
  },
  {
    "id": "B002QG2H7K",
    "title": "Corsair Cooling Hydro Series H50 All In One High-performance CPU Cooler CWCH50-1",
    "link": "https://amazon.com/dp/B002QG2H7K?tag=pcbuildcompat-20",
    "img": "https://images-na.ssl-images-amazon.com/images/I/41aaUuaCrqL._SL75_.jpg",
    "price": 210,
    "brand": "Corsair",
    "model": "CWCH50-1",
    "rpm": "1700 RPM",
    "color": "Black",
    "noiseLevel": "30.32 dB"
  },
  {
    "id": "B002RWJGI6",
    "title": "Thermaltake 7-bladed 92mm 4-Pins PWM Aluminum Extrusion CPU Cooling Fan",
    "link": "https://amazon.com/dp/B002RWJGI6?tag=pcbuildcompat-20",
    "img": "https://images-na.ssl-images-amazon.com/images/I/411GNP-heXL._SL75_.jpg",
    "price": 14.99,
    "brand": "Thermaltake",
    "model": "CLP0556-B",
    "rpm": "1900 - 2300 RPM",
    "color": "Black",
    "noiseLevel": "22 dB"
  },
  {
    "id": "B004XJNC0O",
    "title": "Intel E97379-001 Core I3/i5/i7 Socket 1150/1155/1156 4-Pin Connector CPU Cooler With Aluminum Heatsink And 3.5-Inch Fan For Desktop PC Computer",
    "link": "https://amazon.com/dp/B004XJNC0O?tag=pcbuildcompat-20",
    "img": "https://images-na.ssl-images-amazon.com/images/I/41NAhEfi4vL._SL75_.jpg",
    "price": 12.59,
    "brand": "Intel",
    "model": "E97379-001",
    "rpm": "1200 - 2800 RPM",
    "color": "Black",
    "noiseLevel": "22 dB"
  },
  {
    "id": "B005GGJ5X6",
    "title": "Gelid Solutions 80mm Hydro Dynamic Bearing CPU Cooler",
    "link": "https://amazon.com/dp/B005GGJ5X6?tag=pcbuildcompat-20",
    "img": "https://images-na.ssl-images-amazon.com/images/I/41eeKcjy26L._SL75_.jpg",
    "price": 0,
    "brand": "Gelid Solutions",
    "model": "CC-SIBERIAN-01",
    "rpm": "900 - 2200 RPM",
    "color": "Black / White",
    "noiseLevel": "10 - 22.5 dB"
  },
  {
    "id": "B005O65JXI",
    "title": "Cooler Master Hyper 212 Evo CPU Cooler With PWM Fan, Four Direct Contact Heat Pipes",
    "link": "https://amazon.com/dp/B005O65JXI?tag=pcbuildcompat-20",
    "img": "https://images-na.ssl-images-amazon.com/images/I/51Se9e8gQlL._SL75_.jpg",
    "price": 42.99,
    "brand": "Cooler Master",
    "model": "RR-212E-20PK-R2",
    "rpm": "600 - 2000 RPM",
    "color": "Black",
    "noiseLevel": "9 - 36 dB"
  },
  {
    "id": "B005OREE38",
    "title": "PHANTEKS PH-TC14PE",
    "link": "https://amazon.com/dp/B005OREE38?tag=pcbuildcompat-20",
    "img": "https://images-na.ssl-images-amazon.com/images/I/510u3x6JD9L._SL75_.jpg",
    "price": 77.54,
    "brand": "Phanteks",
    "model": "PH-TC14PE",
    "rpm": "700 - 1200 RPM",
    "color": "White",
    "noiseLevel": "13.4 - 19 dB"
  },
  {
    "id": "B00631QFG8",
    "title": "Noctua NH-D14 SE2011 Quiet CPU Cooler For Intel LGA 2011 Socket With 6 Heatpipes, 140/120mm SSO Bearing PWM Fans NH-D14 SE2011",
    "link": "https://amazon.com/dp/B00631QFG8?tag=pcbuildcompat-20",
    "img": "https://images-na.ssl-images-amazon.com/images/I/51GgkXQSFhL._SL75_.jpg",
    "price": 0,
    "brand": "Noctua",
    "model": "NH-D14 SE2011",
    "rpm": "900 - 1300 RPM",
    "color": "Brown",
    "noiseLevel": "12.6 - 19.8 dB"
  },
  {
    "id": "B007JEMXYQ",
    "title": "DEEPCOOL GAMMAXX 400 CPU Cooler 4 Heatpipes 120mm PWM Fan Blue LED INTEL/AMD AM4 Compatible",
    "link": "https://amazon.com/dp/B007JEMXYQ?tag=pcbuildcompat-20",
    "img": "https://images-na.ssl-images-amazon.com/images/I/51z-3eqjkeL._SL75_.jpg",
    "price": 0,
    "brand": "DEEPCOOL",
    "model": "GAMMAXX 400",
    "rpm": "900 - 1500 RPM",
    "color": "Blue",
    "noiseLevel": "21.4 - 32.1 dB"
  },
  {
    "id": "B009ZN03AA",
    "title": "Corsair Hydro Series Extreme Performance Liquid CPU Cooler H80i",
    "link": "https://amazon.com/dp/B009ZN03AA?tag=pcbuildcompat-20",
    "img": "https://images-na.ssl-images-amazon.com/images/I/41MggvqfOeL._SL75_.jpg",
    "price": 0,
    "brand": "Corsair",
    "model": "CW-9060008-WW",
    "rpm": "2700 RPM",
    "color": "Black",
    "noiseLevel": "37.68 dB"
  },
  {
    "id": "B00BSKY1M4",
    "title": "Cooler Master Hyper RR-T4-18PK-R1 CPU Cooler With 4 Direct Contact Heatpipes, Intel/AMD With AM4 Support",
    "link": "https://amazon.com/dp/B00BSKY1M4?tag=pcbuildcompat-20",
    "img": "https://images-na.ssl-images-amazon.com/images/I/515lk2RatNL._SL75_.jpg",
    "price": 0,
    "brand": "Cooler Master",
    "model": "RR-T4-18PK-R1",
    "rpm": "1800 RPM",
    "color": "Black",
    "noiseLevel": "15.1 - 31.6 dB"
  },
  {
    "id": "B00DWFQ42I",
    "title": "Noctua NH-U12DX I4, Premium CPU Cooler For Intel Xeon LGA20xx",
    "link": "https://amazon.com/dp/B00DWFQ42I?tag=pcbuildcompat-20",
    "img": "https://images-na.ssl-images-amazon.com/images/I/31-B48x97UL._SL75_.jpg",
    "price": 74.95,
    "brand": "Noctua",
    "model": "NH-U12DXi4",
    "rpm": "300 - 1500 RPM",
    "color": "Brown",
    "noiseLevel": "18.6 - 22.4 dB"
  },
  {
    "id": "B00E0EXYDC",
    "title": "Cooler Master V8 GTS - High Performance CPU Cooler With Horizontal Vapor Chamber And 8 Heatpipes",
    "link": "https://amazon.com/dp/B00E0EXYDC?tag=pcbuildcompat-20",
    "img": "https://images-na.ssl-images-amazon.com/images/I/51Xz8lgtSxL._SL75_.jpg",
    "price": 178.21,
    "brand": "Cooler Master",
    "model": "RR-V8VC-16PR-R1",
    "rpm": "1600 RPM",
    "color": "Red",
    "noiseLevel": "36 dB"
  },
  {
    "id": "B00E1JGFA0",
    "title": "Noctua NH-U9DX I4, Premium CPU Cooler For Intel Xeon LGA20xx",
    "link": "https://amazon.com/dp/B00E1JGFA0?tag=pcbuildcompat-20",
    "img": "https://images-na.ssl-images-amazon.com/images/I/51gRfIvdQtL._SL75_.jpg",
    "price": 64.95,
    "brand": "Noctua",
    "model": "NH-U9DXi4",
    "rpm": "300 - 1600 RPM",
    "color": "Brown",
    "noiseLevel": "13.1 - 17.6 dB"
  },
  {
    "id": "B00HPXZF2I",
    "title": "Be Quiet! BK010 Shadow Rock Slim  - CPU Cooler",
    "link": "https://amazon.com/dp/B00HPXZF2I?tag=pcbuildcompat-20",
    "img": "https://images-na.ssl-images-amazon.com/images/I/41v4OgEdtHL._SL75_.jpg",
    "price": 57.5,
    "brand": "be quiet!",
    "model": "BK010",
    "rpm": "400 - 1400 RPM",
    "color": "Black",
    "noiseLevel": "11.5 - 23.7 dB"
  },
  {
    "id": "B00HUHC3WY",
    "title": "Cryorig R1 Ultimate Dual Tower Heatsink For AMD/Intel CPU - Black",
    "link": "https://amazon.com/dp/B00HUHC3WY?tag=pcbuildcompat-20",
    "img": "https://images-na.ssl-images-amazon.com/images/I/41eISyRbq%2BL._SL75_.jpg",
    "price": 0,
    "brand": "Cryorig",
    "model": "CR-R1A",
    "rpm": "700 - 1300 RPM",
    "color": "Black",
    "noiseLevel": "23 dB"
  },
  {
    "id": "B00K7809O2",
    "title": "Cooler Master RR-HT2-28PK-R1 Hyper T2",
    "link": "https://amazon.com/dp/B00K7809O2?tag=pcbuildcompat-20",
    "img": "https://images-na.ssl-images-amazon.com/images/I/41bKDl-fV0L._SL75_.jpg",
    "price": 0,
    "brand": "Cooler Master",
    "model": "RR-HT2-28PK-R1",
    "rpm": "2800 RPM",
    "color": "N/A",
    "noiseLevel": "17 - 35 dB"
  },
  {
    "id": "B00L7UZMAK",
    "title": "Noctua NH-D15, Premium CPU Cooler With 2x NF-A15 PWM 140mm Fans",
    "link": "https://amazon.com/dp/B00L7UZMAK?tag=pcbuildcompat-20",
    "img": "https://images-na.ssl-images-amazon.com/images/I/51ls8fys%2BpL._SL75_.jpg",
    "price": 99.95,
    "brand": "Noctua",
    "model": "NH-D15",
    "rpm": "300 - 1500 RPM",
    "color": "Brown",
    "noiseLevel": "19.2 - 24.6 dB"
  },
  {
    "id": "B00MBTOY2S",
    "title": "Cryorig H5 Universal CR-H5A Mid Tower CPU Heatsink",
    "link": "https://amazon.com/dp/B00MBTOY2S?tag=pcbuildcompat-20",
    "img": "https://images-na.ssl-images-amazon.com/images/I/414LzTeDt4L._SL75_.jpg",
    "price": 109,
    "brand": "Cryorig",
    "model": "FBA_CR-H5A",
    "rpm": "700 - 1300 RPM",
    "color": "White",
    "noiseLevel": "20 - 24 dB"
  },
  {
    "id": "B00MPIDYTO",
    "title": "Thermaltake Water 3.0 Ultimate 360mm Aluminum Radiator Triple Curve Fans",
    "link": "https://amazon.com/dp/B00MPIDYTO?tag=pcbuildcompat-20",
    "img": "https://images-na.ssl-images-amazon.com/images/I/41oKRzX3q9L._SL75_.jpg",
    "price": 0,
    "brand": "Thermaltake",
    "model": "CL-W007-PL12BL-A",
    "rpm": "1000 - 2000 RPM",
    "color": "Black / White",
    "noiseLevel": "20 dB"
  },
  {
    "id": "B00O4UIZ86",
    "title": "Thermaltake Gravity I2 95W Intel LGA 1156/1155/1150/1151 92mm CPU Cooler CLP0556-D",
    "link": "https://amazon.com/dp/B00O4UIZ86?tag=pcbuildcompat-20",
    "img": "https://images-na.ssl-images-amazon.com/images/I/51WRWOGukRL._SL75_.jpg",
    "price": 11.99,
    "brand": "Thermaltake",
    "model": "CLP0556-D",
    "rpm": "1800 RPM",
    "color": "Black / Silver",
    "noiseLevel": "21.3 dB"
  },
  {
    "id": "B00OB40ULU",
    "title": "Be Quiet! BK009 Pure Rock - CPU Cooler",
    "link": "https://amazon.com/dp/B00OB40ULU?tag=pcbuildcompat-20",
    "img": "https://images-na.ssl-images-amazon.com/images/I/41G%2BDhlQ0dL._SL75_.jpg",
    "price": 0,
    "brand": "be quiet!",
    "model": "BK009",
    "rpm": "1500 RPM",
    "color": "N/A",
    "noiseLevel": "19.1 - 26.8 dB"
  },
  {
    "id": "B00PKJ21LW",
    "title": "Thermalright Macho Rev. B",
    "link": "https://amazon.com/dp/B00PKJ21LW?tag=pcbuildcompat-20",
    "img": "https://images-na.ssl-images-amazon.com/images/I/41aCx01EUzL._SL75_.jpg",
    "price": 78.66,
    "brand": "Thermalright",
    "model": "814256001052",
    "rpm": "300 - 1300 RPM",
    "color": "Black / White",
    "noiseLevel": "15 - 21 dB"
  },
  {
    "id": "B00QCEWTAW",
    "title": "Noctua NH-D9L, Premium CPU Cooler With NF-A9 92mm Fan (Brown)",
    "link": "https://amazon.com/dp/B00QCEWTAW?tag=pcbuildcompat-20",
    "img": "https://images-na.ssl-images-amazon.com/images/I/51rO64eeCdL._SL75_.jpg",
    "price": 54.95,
    "brand": "Noctua",
    "model": "NH-D9L",
    "rpm": "400 - 2000 RPM",
    "color": "N/A",
    "noiseLevel": "16.3 - 22.8 dB"
  },
  {
    "id": "B00S7YA5FQ",
    "title": "Cryorig H7 Tower Cooler",
    "link": "https://amazon.com/dp/B00S7YA5FQ?tag=pcbuildcompat-20",
    "img": "https://images-na.ssl-images-amazon.com/images/I/51-dEhr7hJL._SL75_.jpg",
    "price": 35.9,
    "brand": "Cryorig",
    "model": "CR-H7A",
    "rpm": "330 - 1600 RPM",
    "color": "N/A",
    "noiseLevel": "1 - 25 dB"
  },
  {
    "id": "B00TBHYYFK",
    "title": "Noctua NH-U9S, Premium CPU Cooler With NF-A9 92mm Fan",
    "link": "https://amazon.com/dp/B00TBHYYFK?tag=pcbuildcompat-20",
    "img": "https://images-na.ssl-images-amazon.com/images/I/41-NY4DuUdL._SL75_.jpg",
    "price": 59.95,
    "brand": "Noctua",
    "model": "NH-U9S",
    "rpm": "400 - 2000 RPM",
    "color": "Brown",
    "noiseLevel": "16.3 - 22.8 dB"
  },
  {
    "id": "B00V62I9U4",
    "title": "Deep Cool DEEPCOOL CPU Cooler Air 200 W Assassin II, Clear",
    "link": "https://amazon.com/dp/B00V62I9U4?tag=pcbuildcompat-20",
    "img": "https://images-na.ssl-images-amazon.com/images/I/51h2F9pWQEL._SL75_.jpg",
    "price": 0,
    "brand": "DEEPCOOL",
    "model": "6933412725688",
    "rpm": "300 - 1400 RPM",
    "color": "Red",
    "noiseLevel": "17.8 - 27.3 dB"
  },
  {
    "id": "B00VGDN6F6",
    "title": "Be Quiet! Shadow Rock LP",
    "link": "https://amazon.com/dp/B00VGDN6F6?tag=pcbuildcompat-20",
    "img": "https://images-na.ssl-images-amazon.com/images/I/31GaPlNPIxL._SL75_.jpg",
    "price": 49.9,
    "brand": "be quiet!",
    "model": "BK002",
    "rpm": "1500 RPM",
    "color": "Black",
    "noiseLevel": "14.8 - 25.5 dB"
  },
  {
    "id": "B00XUVGLEU",
    "title": "Noctua NH-D15S",
    "link": "https://amazon.com/dp/B00XUVGLEU?tag=pcbuildcompat-20",
    "img": "https://images-na.ssl-images-amazon.com/images/I/51X6arXc8QL._SL75_.jpg",
    "price": 87.99,
    "brand": "Noctua",
    "model": "NH-D15S",
    "rpm": "300 - 1500 RPM",
    "color": "Brown",
    "noiseLevel": "19.2 - 24.6 dB"
  },
  {
    "id": "B00ZTRWPJ8",
    "title": "Thermaltake Water 3.0 Performer",
    "link": "https://amazon.com/dp/B00ZTRWPJ8?tag=pcbuildcompat-20",
    "img": "https://images-na.ssl-images-amazon.com/images/I/31puQamZhIL._SL75_.jpg",
    "price": 0,
    "brand": "Thermaltake",
    "model": "CLW0222-B",
    "rpm": "1200 - 2000 RPM",
    "color": "Black / White",
    "noiseLevel": "27.36 dB"
  },
  {
    "id": "B0154AXB4C",
    "title": "Cryorig H5 Ultimate CR-H5B Middle Range CPU Heatsink With XF140 Fan",
    "link": "https://amazon.com/dp/B0154AXB4C?tag=pcbuildcompat-20",
    "img": "https://images-na.ssl-images-amazon.com/images/I/416k%2BL0vKwL._SL75_.jpg",
    "price": 97.72,
    "brand": "Cryorig",
    "model": "FBA_MICOCR-H5-ULTIMAT",
    "rpm": "700 - 1300 RPM",
    "color": "Black",
    "noiseLevel": "19 - 23 dB"
  },
  {
    "id": "B0196LP24M",
    "title": "Thermaltake Water 3.0 Triple Riing RGB High Static Pressure Fans 360 AIO Liquid Cooling System CPU Cooler CL-W108-PL12SW-A",
    "link": "https://amazon.com/dp/B0196LP24M?tag=pcbuildcompat-20",
    "img": "https://images-na.ssl-images-amazon.com/images/I/51D6ze%2BovuL._SL75_.jpg",
    "price": 0,
    "brand": "Thermaltake",
    "model": "CL-W108-PL12SW-A",
    "rpm": "800 - 1500 RPM",
    "color": "RGB",
    "noiseLevel": "26.4 dB"
  },
  {
    "id": "B019954Y2Q",
    "title": "CORSAIR Hydro Series H80i V2 AIO Liquid CPU Cooler",
    "link": "https://amazon.com/dp/B019954Y2Q?tag=pcbuildcompat-20",
    "img": "https://images-na.ssl-images-amazon.com/images/I/41FTK2kTJAL._SL75_.jpg",
    "price": 239.99,
    "brand": "Corsair",
    "model": "CW-9060024-WW",
    "rpm": "2435 RPM",
    "color": "Black",
    "noiseLevel": "37.7 dB"
  },
  {
    "id": "B019955RNQ",
    "title": "CORSAIR Hydro Series H115i AIO Liquid CPU Cooler, 280mm Radiator, Dual 140mm SP Series PWM Fans, Advanced RGB Lighting And Fan Software Control",
    "link": "https://amazon.com/dp/B019955RNQ?tag=pcbuildcompat-20",
    "img": "https://images-na.ssl-images-amazon.com/images/I/41SEQzRZ3oL._SL75_.jpg",
    "price": 131.7,
    "brand": "Corsair",
    "model": "CW-9060027-WW",
    "rpm": "2000 RPM",
    "color": "Black",
    "noiseLevel": "40 dB"
  },
  {
    "id": "B019EXSSBG",
    "title": "CORSAIR Hydro Series H100i V2 AIO Liquid CPU Cooler, 240mm Radiator, Dual 120mm PWM Fans, Advanced RGB Lighting And Fan Software Control",
    "link": "https://amazon.com/dp/B019EXSSBG?tag=pcbuildcompat-20",
    "img": "https://images-na.ssl-images-amazon.com/images/I/41vt73QuE9L._SL75_.jpg",
    "price": 179,
    "brand": "Corsair",
    "model": "CW-9060025-WW",
    "rpm": "2435 RPM",
    "color": "Black",
    "noiseLevel": "37.7 dB"
  },
  {
    "id": "B01B12DQ38",
    "title": "MasterAir Maker 8 High-end CPU Air Cooler",
    "link": "https://amazon.com/dp/B01B12DQ38?tag=pcbuildcompat-20",
    "img": "https://images-na.ssl-images-amazon.com/images/I/517-394kT6L._SL75_.jpg",
    "price": 0,
    "brand": "Cooler Master",
    "model": "MAZ-T8PN-418PR-R1",
    "rpm": "600 - 1800 RPM",
    "color": "Red / Black",
    "noiseLevel": "8 - 24 dB"
  },
  {
    "id": "B01BCLXO7Q",
    "title": "Thermalright Le Grand Macho RT (with Fan TY-147B)",
    "link": "https://amazon.com/dp/B01BCLXO7Q?tag=pcbuildcompat-20",
    "img": "https://images-na.ssl-images-amazon.com/images/I/41r3O%2BhlahL._SL75_.jpg",
    "price": 69.99,
    "brand": "Thermalright",
    "model": "100700733",
    "rpm": "300 - 1300 RPM",
    "color": "Black / Silver",
    "noiseLevel": "14 - 20 dB"
  },
  {
    "id": "B01HGMHVAQ",
    "title": "DeepCool Gamer Storm CPU Liquid Cooler AIO Water Cooling (Captain 240 EX)",
    "link": "https://amazon.com/dp/B01HGMHVAQ?tag=pcbuildcompat-20",
    "img": "https://images-na.ssl-images-amazon.com/images/I/41K0CaLGGyL._SL75_.jpg",
    "price": 0,
    "brand": "DEEPCOOL",
    "model": "CAPTAIN 240 EX",
    "rpm": "500 - 1800 RPM",
    "color": "Red / Black",
    "noiseLevel": "17.6 - 31.3 dB"
  },
  {
    "id": "B01HLAHDWE",
    "title": "Antec A30, 0-761345-10922-2",
    "link": "https://amazon.com/dp/B01HLAHDWE?tag=pcbuildcompat-20",
    "img": "https://images-na.ssl-images-amazon.com/images/I/519fmJ7-YJL._SL75_.jpg",
    "price": 18.99,
    "brand": "Antec",
    "model": "0-761345-10922-2",
    "rpm": "2000 RPM",
    "color": "Black",
    "noiseLevel": "20 dBA"
  },
  {
    "id": "B01HQ6DB4W",
    "title": "Alphacool 11285 Eisbaer 240 CPU - Black Water Cooling Kits, Systems And AIOs",
    "link": "https://amazon.com/dp/B01HQ6DB4W?tag=pcbuildcompat-20",
    "img": "https://images-na.ssl-images-amazon.com/images/I/41rMcDddfuL._SL75_.jpg",
    "price": 120.78,
    "brand": "Alphacool",
    "model": "11285",
    "rpm": "550 - 1700 RPM",
    "color": "N/A",
    "noiseLevel": "29 dB"
  },
  {
    "id": "B01J4ZG6RC",
    "title": "DEEPCOOL Captain 360EX All-in-One Liquid CPU Cooler",
    "link": "https://amazon.com/dp/B01J4ZG6RC?tag=pcbuildcompat-20",
    "img": "https://images-na.ssl-images-amazon.com/images/I/41jfwi6ZTWL._SL75_.jpg",
    "price": 0,
    "brand": "DEEPCOOL",
    "model": "DEEPCOOL CAPTAIN 360EX",
    "rpm": "500 - 1800 RPM",
    "color": "Red / Black",
    "noiseLevel": "17.6 - 31.3 dB"
  },
  {
    "id": "B01KBXKP8W",
    "title": "Cooler Master RR-212L-16PR-R1 Hyper 212 LED",
    "link": "https://amazon.com/dp/B01KBXKP8W?tag=pcbuildcompat-20",
    "img": "https://images-na.ssl-images-amazon.com/images/I/51X4o7Z650L._SL75_.jpg",
    "price": 48,
    "brand": "Cooler Master",
    "model": "RR-212L-16PR-R1",
    "rpm": "600 - 1600 RPM",
    "color": "Red",
    "noiseLevel": "9 - 31 dB"
  },
  {
    "id": "B01KVNCEIG",
    "title": "Be Quiet! BK008 Pure Rock Slim - CPU Cooler",
    "link": "https://amazon.com/dp/B01KVNCEIG?tag=pcbuildcompat-20",
    "img": "https://images-na.ssl-images-amazon.com/images/I/51nJWy791pL._SL75_.jpg",
    "price": 0,
    "brand": "be quiet!",
    "model": "BK008",
    "rpm": "2000 RPM",
    "color": "N/A",
    "noiseLevel": "13.1 - 25.4 dB"
  },
  {
    "id": "B01M0TJIAA",
    "title": "Be Quiet Silent CPU Cooler Silent Loop 120mm",
    "link": "https://amazon.com/dp/B01M0TJIAA?tag=pcbuildcompat-20",
    "img": "https://images-na.ssl-images-amazon.com/images/I/41W2NGI%2BxlL._SL75_.jpg",
    "price": 0,
    "brand": "be quiet!",
    "model": "T380658",
    "rpm": "2000 RPM",
    "color": "black",
    "noiseLevel": "16.1 - 36.9 dB"
  },
  {
    "id": "B01M191GRY",
    "title": "NZXT Kraken X52 All-in-One CPU Liquid Cooling System Cooling",
    "link": "https://amazon.com/dp/B01M191GRY?tag=pcbuildcompat-20",
    "img": "https://images-na.ssl-images-amazon.com/images/I/41h3eMKxdGL._SL75_.jpg",
    "price": 0,
    "brand": "NZXT",
    "model": "RL-KRX52-01",
    "rpm": "500 - 2000 RPM",
    "color": "Black",
    "noiseLevel": "21 - 36 dB"
  },
  {
    "id": "B01M1B4BQ5",
    "title": "Cooler Master MasterLiquid Pro 280 CPU Cooler",
    "link": "https://amazon.com/dp/B01M1B4BQ5?tag=pcbuildcompat-20",
    "img": "https://images-na.ssl-images-amazon.com/images/I/51paJ%2BK2WwL._SL75_.jpg",
    "price": 99,
    "brand": "Cooler Master",
    "model": "MLY-D28M-A22MB-R1",
    "rpm": "650 - 2200 RPM",
    "color": "Black",
    "noiseLevel": "6 - 30 dB"
  },
  {
    "id": "B01MFB358A",
    "title": "MSI CPU Cooler",
    "link": "https://amazon.com/dp/B01MFB358A?tag=pcbuildcompat-20",
    "img": "https://images-na.ssl-images-amazon.com/images/I/51bbZFz-pPL._SL75_.jpg",
    "price": 0,
    "brand": "MSI",
    "model": "MSI Core Frozr L",
    "rpm": "500 - 1800 RPM",
    "color": "Black / Silver",
    "noiseLevel": "17.2 - 33.6 dB"
  },
  {
    "id": "B01N16CAKN",
    "title": "EVGA CLC 280mm All-In-One RGB LED CPU Liquid Cooler",
    "link": "https://amazon.com/dp/B01N16CAKN?tag=pcbuildcompat-20",
    "img": "https://images-na.ssl-images-amazon.com/images/I/51YzeLS0uyL._SL75_.jpg",
    "price": 109.99,
    "brand": "EVGA",
    "model": "400-HY-CL28-V1",
    "rpm": "600 - 2200 RPM",
    "color": "Black",
    "noiseLevel": "16 - 39.5 dB"
  },
  {
    "id": "B01N2NMUWJ",
    "title": "DeepCool NEPTWIN White Version CPU Cooler 6 Heat Pipes",
    "link": "https://amazon.com/dp/B01N2NMUWJ?tag=pcbuildcompat-20",
    "img": "https://images-na.ssl-images-amazon.com/images/I/51uvvtSWvkL._SL75_.jpg",
    "price": 0,
    "brand": "DEEPCOOL",
    "model": "NEPTWIN White",
    "rpm": "900 - 1500 RPM",
    "color": "White",
    "noiseLevel": "17.8 - 30 dB"
  },
  {
    "id": "B01N9X3HY1",
    "title": "EVGA CLC 120 Liquid/Water CPU Cooler, RGB LED Cooling 400-HY-CL12-V1",
    "link": "https://amazon.com/dp/B01N9X3HY1?tag=pcbuildcompat-20",
    "img": "https://images-na.ssl-images-amazon.com/images/I/41A4DhoCe0L._SL75_.jpg",
    "price": 0,
    "brand": "EVGA",
    "model": "400-HY-CL12-V1",
    "rpm": "500 - 2400 RPM",
    "color": "Black",
    "noiseLevel": "16 - 39.9 dB"
  }
]